ttblit/__init__.py
ttblit/__main__.py
ttblit/asset/__init__.py
ttblit/asset/builder.py
ttblit/asset/formatter.py
ttblit/asset/writer.py
ttblit/asset/builders/__init__.py
ttblit/asset/builders/font.py
ttblit/asset/builders/image.py
ttblit/asset/builders/map.py
ttblit/asset/builders/raw.py
ttblit/asset/formatters/__init__.py
ttblit/asset/formatters/c.py
ttblit/asset/formatters/raw.py
ttblit/core/__init__.py
ttblit/core/blitserial.py
ttblit/core/compression.py
ttblit/core/dfu.py
ttblit/core/palette.py
ttblit/core/struct.py
ttblit/core/yamlloader.py
ttblit/tool/__init__.py
ttblit/tool/cmake.py
ttblit/tool/dfu.py
ttblit/tool/flasher.py
ttblit/tool/metadata.py
ttblit/tool/packer.py
ttblit/tool/relocs.py
ttblit/tool/setup.py
32blit-0.7.4.dist-info/LICENSE.txt
32blit-0.7.4.dist-info/METADATA
32blit-0.7.4.dist-info/WHEEL
32blit-0.7.4.dist-info/entry_points.txt
32blit-0.7.4.dist-info/top_level.txt
32blit-0.7.4.dist-info/RECORD
