Metadata-Version: 2.1
Name: 32blit
Version: 0.7.4
Summary: 32Blit asset preparation and upload tools
Home-page: https://32blit.com
Author: Philip Howard
Author-email: phil@pimoroni.com
License: MIT
Project-URL: GitHub, https://www.github.com/pimoroni/32blit-tools
Project-URL: Twitter, https://twitter.com/32blit
Keywords: 32Blit CLI
Platform: any
Classifier: Development Status :: 4 - Beta
Classifier: Operating System :: POSIX :: Linux
Classifier: License :: OSI Approved :: MIT License
Classifier: Intended Audience :: Developers
Classifier: Programming Language :: Python :: 3
Classifier: Topic :: Software Development
Classifier: Topic :: Software Development :: Libraries
Classifier: Topic :: System :: Hardware
Requires-Python: >=3.4
License-File: LICENSE.txt
Requires-Dist: click (>=7)
Requires-Dist: pillow
Requires-Dist: pyyaml
Requires-Dist: bitstring
Requires-Dist: pyserial
Requires-Dist: tqdm
Requires-Dist: freetype-py
Requires-Dist: construct (>=2.9)
Requires-Dist: pyelftools
